machine/__init__.py
machine/connection.py
machine/enums.py
machine/machine.py
machine/params.py
machine/path.py
machine/plugin.py
machine/resource.py
machine/test_client.py
machine/types.py
machine/exceptions/__init__.py
machine/exceptions/connection.py
machine/exceptions/machine.py
machine/exceptions/resource.py
machine/exceptions/plugins/__init__.py
machine/exceptions/plugins/accept.py
machine/exceptions/plugins/conn_type.py
machine/exceptions/plugins/jsonrpc.py
machine/exceptions/plugins/options.py
machine/exceptions/plugins/path.py
machine/plugins/__init__.py
machine/plugins/accepts.py
machine/plugins/conn_type.py
machine/plugins/content_type.py
machine/plugins/dependency.py
machine/plugins/method.py
machine/plugins/options.py
machine/plugins/path.py
machine/plugins/sequence.py
machine/plugins/jsonrpc/__init__.py
machine/plugins/jsonrpc/error_plugin.py
machine/plugins/jsonrpc/handler.py
machine/plugins/jsonrpc/resource.py
machine/plugins/rest/__init__.py
machine/plugins/rest/error_plugin.py
machine/plugins/rest/error_renderer.py
machine/plugins/rest/handler.py
machine/plugins/rest/method_selector.py
machine/plugins/rest/request.py
machine/plugins/rest/resource.py
machine/plugins/rest/response.py
machine/utils/__init__.py
machine/utils/either.py
machine_web-0.0.2.post2.dist-info/LICENSE
machine_web-0.0.2.post2.dist-info/METADATA
machine_web-0.0.2.post2.dist-info/WHEEL
machine_web-0.0.2.post2.dist-info/top_level.txt
machine_web-0.0.2.post2.dist-info/RECORD
